CyberSecurityTools/__init__.py
CyberSecurityTools/broken_link_checker.py
CyberSecurityTools/csrf_tester.py
CyberSecurityTools/main.py
CyberSecurityTools/network_vulnerability_scanner.py
CyberSecurityTools/sql_injection_tester.py
CyberSecurityTools/subdomain_enumeration.py
CyberSecurityTools/xss_tester.py
CyberSecurityTools-0.3.dist-info/LICENSE
CyberSecurityTools-0.3.dist-info/METADATA
CyberSecurityTools-0.3.dist-info/WHEEL
CyberSecurityTools-0.3.dist-info/top_level.txt
CyberSecurityTools-0.3.dist-info/RECORD
